{"nodes": [{"id": "index_app_shell", "label": "TeamSync App Shell (Main UI)", "file_type": "code", "source_file": "index.html", "source_location": null, "source_url": null, "captured_at": null, "author": null, "contributor": null}, {"id": "index_device_auth_step", "label": "Device Auth Login Step", "file_type": "code", "source_file": "index.html", "source_location": null, "source_url": null, "captured_at": null, "author": null, "contributor": null}, {"id": "index_friends_dm", "label": "Friends & Direct Messaging", "file_type": "code", "source_file": "index.html", "source_location": null, "source_url": null, "captured_at": null, "author": null, "contributor": null}, {"id": "index_join_create_server", "label": "Join / Create Server Flow", "file_type": "code", "source_file": "index.html", "source_location": null, "source_url": null, "captured_at": null, "author": null, "contributor": null}, {"id": "index_relay_option", "label": "Relay (TURN) Option", "file_type": "rationale", "source_file": "index.html", "source_location": null, "source_url": null, "captured_at": null, "author": null, "contributor": null}, {"id": "index_rnnoise_option", "label": "RNNoise Toggle Option", "file_type": "concept", "source_file": "index.html", "source_location": null, "source_url": null, "captured_at": null, "author": null, "contributor": null}, {"id": "index_game_mode", "label": "Game Mode (Lite Performance)", "file_type": "rationale", "source_file": "index.html", "source_location": null, "source_url": null, "captured_at": null, "author": null, "contributor": null}, {"id": "index_pokemon_battle", "label": "Pokemon Battle Mini-Game", "file_type": "code", "source_file": "index.html", "source_location": null, "source_url": null, "captured_at": null, "author": null, "contributor": null}, {"id": "index_pokeapi_sprite_fallback", "label": "Pokemon Sprite Fallback Chain", "file_type": "rationale", "source_file": "index.html", "source_location": null, "source_url": null, "captured_at": null, "author": null, "contributor": null}, {"id": "index_emqx_broker", "label": "EMQX MQTT Signaling Broker", "file_type": "concept", "source_file": "index.html", "source_location": null, "source_url": null, "captured_at": null, "author": null, "contributor": null}, {"id": "index_supabase_backend", "label": "Supabase Backend Endpoint", "file_type": "concept", "source_file": "index.html", "source_location": null, "source_url": null, "captured_at": null, "author": null, "contributor": null}, {"id": "index_bitrate_quality", "label": "Audio Quality (Bitrate) Setting", "file_type": "concept", "source_file": "index.html", "source_location": null, "source_url": null, "captured_at": null, "author": null, "contributor": null}, {"id": "index_custom_titlebar", "label": "Custom Electron Titlebar", "file_type": "code", "source_file": "index.html", "source_location": null, "source_url": null, "captured_at": null, "author": null, "contributor": null}], "edges": [{"source": "index_app_shell", "target": "index_device_auth_step", "relation": "references", "confidence": "EXTRACTED", "confidence_score": 1.0, "source_file": "index.html", "source_location": null, "weight": 1.0}, {"source": "index_app_shell", "target": "index_friends_dm", "relation": "references", "confidence": "EXTRACTED", "confidence_score": 1.0, "source_file": "index.html", "source_location": null, "weight": 1.0}, {"source": "index_app_shell", "target": "index_join_create_server", "relation": "references", "confidence": "EXTRACTED", "confidence_score": 1.0, "source_file": "index.html", "source_location": null, "weight": 1.0}, {"source": "index_app_shell", "target": "index_custom_titlebar", "relation": "references", "confidence": "EXTRACTED", "confidence_score": 1.0, "source_file": "index.html", "source_location": null, "weight": 1.0}, {"source": "index_join_create_server", "target": "index_relay_option", "relation": "references", "confidence": "EXTRACTED", "confidence_score": 1.0, "source_file": "index.html", "source_location": null, "weight": 1.0}, {"source": "index_join_create_server", "target": "index_rnnoise_option", "relation": "references", "confidence": "EXTRACTED", "confidence_score": 1.0, "source_file": "index.html", "source_location": null, "weight": 1.0}, {"source": "index_join_create_server", "target": "index_game_mode", "relation": "references", "confidence": "EXTRACTED", "confidence_score": 1.0, "source_file": "index.html", "source_location": null, "weight": 1.0}, {"source": "index_join_create_server", "target": "index_bitrate_quality", "relation": "references", "confidence": "EXTRACTED", "confidence_score": 1.0, "source_file": "index.html", "source_location": null, "weight": 1.0}, {"source": "index_pokemon_battle", "target": "index_pokeapi_sprite_fallback", "relation": "references", "confidence": "EXTRACTED", "confidence_score": 1.0, "source_file": "index.html", "source_location": null, "weight": 1.0}, {"source": "index_app_shell", "target": "index_emqx_broker", "relation": "references", "confidence": "INFERRED", "confidence_score": 0.85, "source_file": "index.html", "source_location": null, "weight": 1.0}, {"source": "index_app_shell", "target": "index_supabase_backend", "relation": "references", "confidence": "INFERRED", "confidence_score": 0.75, "source_file": "index.html", "source_location": null, "weight": 1.0}, {"source": "index_app_shell", "target": "readme_teamsync", "relation": "conceptually_related_to", "confidence": "INFERRED", "confidence_score": 0.95, "source_file": "index.html", "source_location": null, "weight": 1.0}], "hyperedges": [{"id": "teamsync_serverless_p2p_identity", "label": "Serverless P2P Communication Platform", "nodes": ["readme_p2p_serverless", "docs_index_p2p_voice_video", "index_relay_option", "index_emqx_broker"], "relation": "form", "confidence": "INFERRED", "confidence_score": 0.75, "source_file": "index.html"}]}